PyMaxflow-1.3.2.dist-info/top_level.txt
PyMaxflow-1.3.2.dist-info/RECORD
PyMaxflow-1.3.2.dist-info/METADATA
PyMaxflow-1.3.2.dist-info/WHEEL
maxflow/__init__.py
maxflow/_maxflow.cpython-39-x86_64-linux-gnu.so
maxflow/fastmin.py
maxflow/version.py
